listvideo/__init__.py
listvideo/src/__init__.py
listvideo/src/app.py
listvideo/src/exceptions.py
listvideo/src/models.py
listvideo/src/data/__init__.py
listvideo/src/data/cache.py
listvideo/src/data/metadata.py
listvideo/src/routes/__init__.py
listvideo/src/routes/channels.py
listvideo/src/routes/index.py
listvideo/src/routes/videos.py
listvideo/src/routes/utils/__init__.py
listvideo/src/routes/utils/cache.py
listvideo-0.0.1.dist-info/LICENSE
listvideo-0.0.1.dist-info/METADATA
listvideo-0.0.1.dist-info/WHEEL
listvideo-0.0.1.dist-info/top_level.txt
listvideo-0.0.1.dist-info/RECORD
