Metadata-Version: 2.1
Name: listvideo
Version: 0.0.1
Summary: ListVideo es una biblioteca que facilita la interacción con las listas de reproducción de YouTube. Permite acceder a los metadatos de los videos y organizarlos de manera eficiente.
Author-email: Francisco Griman <grihardware@gmail.com>
License: MIT License
Project-URL: Homepage, https://github.com/fcoagz/listvideo
Project-URL: Bug Tracker, https://github.com/fcoagz/listvideo/issues
Keywords: youtube,playlist,video
Classifier: Programming Language :: Python :: 3
Classifier: License :: OSI Approved :: MIT License
Classifier: Operating System :: OS Independent
Requires-Python: >=3.9
License-File: LICENSE
Requires-Dist: flask
Requires-Dist: flask-cors
Requires-Dist: pytube
Requires-Dist: cachetools
